pydv/__init__.py
pydv/curve.py
pydv/img/app_icon3.png
pydv/img/window-code-7.png
pydv/img/window-code-7@2x.png
pydv/pdv
pydv/pdv.py
pydv/pdv_launcher.py
pydv/pdvnavbar.py
pydv/pdvplot.py
pydv/pdvutil.py
pydv/pydvpy.py
pydv/scripts/date.txt
pydv/scripts/update_version_and_date.py
pydv/scripts/version.txt
llnl_pydv-3.8.2.dist-info/METADATA
llnl_pydv-3.8.2.dist-info/WHEEL
llnl_pydv-3.8.2.dist-info/entry_points.txt
llnl_pydv-3.8.2.dist-info/licenses/LICENSE
llnl_pydv-3.8.2.dist-info/RECORD
