Metadata-Version: 2.4
Name: LLNL-PyDV
Version: 3.8.2
Summary: PyDV: Python Data Visualizer
License: BSD
License-File: LICENSE
Author: Jorge Moreno
Author-email: moreno45@llnl.gov
Maintainer: Jorge Moreno
Maintainer-email: moreno45@llnl.gov
Requires-Python: >=3.9
Classifier: Development Status :: 5 - Production/Stable
Classifier: Intended Audience :: Developers
Classifier: Intended Audience :: End Users/Desktop
Classifier: Intended Audience :: Science/Research
Classifier: License :: OSI Approved :: BSD License
Classifier: License :: Other/Proprietary License
Classifier: Operating System :: OS Independent
Classifier: Programming Language :: Python :: 3
Classifier: Programming Language :: Python :: 3.9
Classifier: Programming Language :: Python :: 3.10
Classifier: Programming Language :: Python :: 3.11
Classifier: Programming Language :: Python :: 3.12
Classifier: Programming Language :: Python :: 3.13
Classifier: Programming Language :: Python :: 3.14
Classifier: Topic :: Scientific/Engineering
Classifier: Topic :: Scientific/Engineering :: Mathematics
Requires-Dist: PyQt6
Requires-Dist: matplotlib
Requires-Dist: numpy
Requires-Dist: scikit-image
Requires-Dist: scikit-learn
Requires-Dist: scipy
Project-URL: Bug Tracker, https://github.com/LLNL/PyDV/issues
Project-URL: Documentation, https://pydv.readthedocs.io/en/latest/
Project-URL: Discussions, https://github.com/LLNL/PyDV/discussions
Project-URL: Homepage, https://github.com/LLNL/PyDV
